adbili/__init__.py
adbili/command.py
adbili/constant.py
adbili/main.py
adbili/utils.py
adbili/devices/__init__.py
adbili/devices/adb.py
adbili/devices/atx.py
adbili/devices/base.py
adbili-1.0.0.dist-info/METADATA
adbili-1.0.0.dist-info/WHEEL
adbili-1.0.0.dist-info/entry_points.txt
adbili-1.0.0.dist-info/RECORD
