Metadata-Version: 2.4
Name: adbili
Version: 1.0.0
Summary: adb copier for bilibili songs/audios
Author-email: Hugh <hugh.lpd@gmail.com>
Requires-Python: >=3.11
Requires-Dist: fire>=0.7.0
